firestoreMQ/__init__.py
firestoreMQ/firestoreMQ.py
lib/__init__.py
lib/firestoreMQ.py
firestoreMQ-1.0.dist-info/LICENSE
firestoreMQ-1.0.dist-info/METADATA
firestoreMQ-1.0.dist-info/WHEEL
firestoreMQ-1.0.dist-info/top_level.txt
firestoreMQ-1.0.dist-info/RECORD
