Metadata-Version: 2.1
Name: firestoreMQ
Version: 1.0
Summary: Firestore MQ python library
Home-page: UNKNOWN
Author: Alex Robinson
Author-email: alex@arrx.uk
License: UNKNOWN
Platform: UNKNOWN
Classifier: Programming Language :: Python :: 3
Classifier: License :: OSI Approved :: MIT License
Classifier: Operating System :: OS Independent
